article_forestz/__init__.py
article_forestz/article_decision.py
article_forestz/llm.py
article_forestz/tree.py
article_forestz-0.1.2.dist-info/METADATA
article_forestz-0.1.2.dist-info/WHEEL
article_forestz-0.1.2.dist-info/top_level.txt
article_forestz-0.1.2.dist-info/RECORD
