Metadata-Version: 2.4
Name: article-forestz
Version: 0.1.2
Summary: Add your description here
Requires-Python: >=3.13
Requires-Dist: black>=25.1.0
Requires-Dist: graphviz>=0.20.3
Requires-Dist: llmada>=0.1.11
Requires-Dist: toml>=0.10.2
